{"skeleton":{"hash":"pFuRYgISHBovkoLOPWnsZ3nVzyg","spine":"3.7.91","width":208,"height":215.7,"images":"./image/","audio":""},"bones":[{"name":"root"},{"name":"WILD_text","parent":"root","x":180,"y":-184.66},{"name":"D","parent":"WILD_text","length":25.3,"rotation":90,"x":-44.5,"y":-10.7},{"name":"I","parent":"WILD_text","length":25.58,"rotation":90,"x":-86.48,"y":-10.42},{"name":"L","parent":"WILD_text","length":25.3,"rotation":91.26,"x":-69.8,"y":-10.42},{"name":"W","parent":"WILD_text","length":25.58,"rotation":89.38,"x":-109.27,"y":-10.7},{"name":"wild_text_BLINKS","parent":"WILD_text","x":-243.15,"y":55.99},{"name":"blink","parent":"wild_text_BLINKS","x":117,"y":-43.29,"scaleX":1.689,"scaleY":1.689},{"name":"blink2","parent":"wild_text_BLINKS","x":161.07,"y":-51.48,"scaleX":0.943,"scaleY":0.943},{"name":"blink3","parent":"wild_text_BLINKS","x":189.15,"y":-43.68,"scaleX":1.279,"scaleY":1.279},{"name":"blink gun","parent":"root"},{"name":"body","parent":"root","length":50,"rotation":91.27,"x":146.31,"y":-191.25},{"name":"neck","parent":"body","length":20,"rotation":18.19,"x":72.4,"y":3.28},{"name":"head2","parent":"neck","length":30,"rotation":-3.89,"x":20.99,"y":-0.38},{"name":"eteRight","parent":"head2","length":5,"rotation":11.43,"x":29.75,"y":14.74,"color":"000000ff"},{"name":"glow","parent":"WILD_text","x":-79.53,"y":9.32},{"name":"hair1","parent":"head2","length":30,"rotation":-148.43,"x":63.66,"y":24.32,"color":"ff7b2eff"},{"name":"hair2","parent":"head2","length":30,"rotation":174.35,"x":35.92,"y":-5.16,"color":"ff7b2eff"},{"name":"hair3","parent":"head2","length":30,"rotation":144.07,"x":64.5,"y":30.1,"color":"ff7b2eff"},{"name":"hair4","parent":"head2","length":30,"rotation":163.39,"x":32.97,"y":37.68,"color":"ff7b2eff"},{"name":"hoop back","parent":"head2","rotation":11.43,"x":6.3,"y":34.64},{"name":"hoop front","parent":"head2","rotation":11.43,"x":0.85,"y":-6.44},{"name":"knife hand","parent":"root","length":70,"rotation":129.33,"x":110.06,"y":-229.17},{"name":"knife hand2","parent":"knife hand","length":20,"rotation":25.3,"x":70.65,"y":0.72},{"name":"right hand","parent":"body","length":55,"rotation":28.2,"x":2.18,"y":45.74},{"name":"right hand2","parent":"right hand","length":20,"x":61.29},{"name":"right hand finger1","parent":"right hand2","length":10,"rotation":-18.38,"x":21.83},{"name":"right hand finger2","parent":"right hand finger1","length":8,"rotation":35.94,"x":10.74,"y":-0.33},{"name":"right hand finger3","parent":"right hand finger2","length":10,"rotation":26.1,"x":8.75,"y":0.64},{"name":"target","parent":"root","x":-12.05,"y":-87.91,"color":"ff0000ff"},{"name":"D2","parent":"WILD_text","rotation":90,"x":-44.5,"y":-10.7,"color":"ff0000ff"},{"name":"I2","parent":"WILD_text","rotation":90,"x":-86.48,"y":-10.42,"color":"ff0000ff"},{"name":"L2","parent":"WILD_text","rotation":91.26,"x":-69.8,"y":-10.42,"color":"ff0000ff"},{"name":"W2","parent":"WILD_text","rotation":89.38,"x":-109.27,"y":-10.7,"color":"ff0000ff"}],"slots":[{"name":"frame","bone":"root"},{"name":"frame_new","bone":"root","attachment":"frame_new"},{"name":"mask","bone":"root","attachment":"mask"},{"name":"right hand","bone":"right hand","attachment":"prawa reka"},{"name":"knife hand","bone":"knife hand","attachment":"lewa reka"},{"name":"body","bone":"body","attachment":"body"},{"name":"wlos 4","bone":"hair4","attachment":"wlos 4"},{"name":"hoop back","bone":"hoop back","attachment":"hoop 2"},{"name":"head","bone":"head2","attachment":"head"},{"name":"frame_up","bone":"root","attachment":"frame_up"},{"name":"D","bone":"D","attachment":"D"},{"name":"D2","bone":"D2","color":"ffffff00","attachment":"D","blend":"additive"},{"name":"L","bone":"L","attachment":"L"},{"name":"L2","bone":"L2","color":"ffffff00","attachment":"L","blend":"additive"},{"name":"I","bone":"I","attachment":"I"},{"name":"I2","bone":"I2","color":"ffffff00","attachment":"I","blend":"additive"},{"name":"W","bone":"W","attachment":"W"},{"name":"W2","bone":"W2","color":"ffffff00","attachment":"W","blend":"additive"},{"name":"wild_glow","bone":"glow","attachment":"wild_glow","blend":"additive"},{"name":"blink","bone":"blink","color":"ffffff00","attachment":"blink","blend":"additive"},{"name":"blink3","bone":"blink2","color":"ffffff00","attachment":"blink","blend":"additive"},{"name":"blink4","bone":"blink3","color":"ffffff00","attachment":"blink","blend":"additive"},{"name":"blink2","bone":"blink gun","color":"ffffff00","attachment":"blink","blend":"additive"},{"name":"eye","bone":"eteRight","color":"ffffff00","attachment":"eye"},{"name":"hoop front","bone":"hoop front","attachment":"hoop front"},{"name":"wlos 1","bone":"hair1","attachment":"wlos 1"},{"name":"wlos 3","bone":"hair3","attachment":"wlos 3"},{"name":"wlos 2","bone":"hair2","attachment":"wlos2"},{"name":"sym1_3","bone":"root","color":"ffffff00"},{"name":"frame_new_add","bone":"root","color":"ffffff00","attachment":"frame_new","blend":"additive"}],"skins":{"default":{"D":{"D":{"type":"mesh","uvs":[1,1,0,1,0,0,1,0],"triangles":[1,2,3,1,3,0],"vertices":[1,2,-5.25,-19.65,1,1,2,-5.25,16.35,1,1,2,26.75,16.35,1,1,2,26.75,-19.65,1],"hull":4,"edges":[0,2,2,4,4,6,0,6],"width":36,"height":32}},"D2":{"D":{"type":"mesh","uvs":[1,1,0,1,0,0,1,0],"triangles":[1,2,3,1,3,0],"vertices":[1,30,-5.25,-19.65,1,1,30,-5.25,16.35,1,1,30,26.75,16.35,1,1,30,26.75,-19.65,1],"hull":4,"edges":[0,2,2,4,4,6,0,6],"width":36,"height":32}},"I":{"I":{"type":"mesh","uvs":[1,1,0,1,0,0,1,0],"triangles":[1,2,3,1,3,0],"vertices":[1,3,-2.86,-9.06,1,1,3,-2.86,6.94,1,1,3,26.14,6.94,1,1,3,26.14,-9.06,1],"hull":4,"edges":[0,2,2,4,4,6,0,6],"width":16,"height":29}},"I2":{"I":{"type":"mesh","uvs":[1,1,0,1,0,0,1,0],"triangles":[1,2,3,1,3,0],"vertices":[1,31,-2.86,-9.06,1,1,31,-2.86,6.94,1,1,31,26.14,6.94,1,1,31,26.14,-9.06,1],"hull":4,"edges":[0,2,2,4,4,6,0,6],"width":16,"height":29}},"L":{"L":{"type":"mesh","uvs":[1,1,0,1,0,0,1,0],"triangles":[1,2,3,1,3,0],"vertices":[1,4,-4.98,-15.58,1,1,4,-4.39,11.42,1,1,4,26.61,10.74,1,1,4,26.01,-16.26,1],"hull":4,"edges":[0,2,2,4,4,6,0,6],"width":27,"height":31}},"L2":{"L":{"type":"mesh","uvs":[1,1,0,1,0,0,1,0],"triangles":[1,2,3,1,3,0],"vertices":[1,32,-4.98,-15.58,1,1,32,-4.39,11.42,1,1,32,26.61,10.74,1,1,32,26.01,-16.26,1],"hull":4,"edges":[0,2,2,4,4,6,0,6],"width":27,"height":31}},"W":{"W":{"type":"mesh","uvs":[1,1,0,1,0,0,1,0],"triangles":[1,2,3,1,3,0],"vertices":[1,5,-4.83,-51.51,1,1,5,-5.63,21.48,1,1,5,26.37,21.83,1,1,5,27.16,-51.16,1],"hull":4,"edges":[0,2,2,4,4,6,0,6],"width":73,"height":32}},"W2":{"W":{"type":"mesh","uvs":[1,1,0,1,0,0,1,0],"triangles":[1,2,3,1,3,0],"vertices":[1,33,-4.83,-51.51,1,1,33,-5.63,21.48,1,1,33,26.37,21.83,1,1,33,27.16,-51.16,1],"hull":4,"edges":[0,2,2,4,4,6,0,6],"width":73,"height":32}},"blink":{"blink":{"type":"mesh","uvs":[1,1,0,1,0,0,1,0],"triangles":[1,2,3,1,3,0],"vertices":[8.76,-9.43,-7.24,-9.43,-7.24,8.57,8.76,8.57],"hull":4,"edges":[0,2,2,4,4,6,0,6],"width":16,"height":18}},"blink2":{"blink":{"width":16,"height":18}},"blink3":{"blink":{"type":"mesh","uvs":[1,1,0,1,0,0,1,0],"triangles":[1,2,3,1,3,0],"vertices":[8.76,-9.43,-7.24,-9.43,-7.24,8.57,8.76,8.57],"hull":4,"edges":[0,2,2,4,4,6,0,6],"width":16,"height":18}},"blink4":{"blink":{"type":"mesh","uvs":[1,1,0,1,0,0,1,0],"triangles":[1,2,3,1,3,0],"vertices":[8.76,-9.43,-7.24,-9.43,-7.24,8.57,8.76,8.57],"hull":4,"edges":[0,2,2,4,4,6,0,6],"width":16,"height":18}},"body":{"body":{"type":"mesh","uvs":[1,0.53332,1,0.61305,1,1,0.89227,1,0.73365,1,0.56718,1,0,1,0,0,0.34823,0,0.52008,0,0.64674,0,1,0,0.54149,0.35646,0.77569,0.20552,0.91346,0.35465,0.47683,0.31496,0.42065,0.32217,0.35177,0.4211,0.33057,0.51117,0.42949,0.51708,0.65911,0.33546,0.75626,0.27197,0.81455,0.45063,0.63903,0.56132,0.32329,0.59773,0.2732,0.67964,0.26449,0.77976,0.21223,0.58134,0.14908,0.64688,0.13602,0.73607,0.17957,0.77248,0.67387,0.46302,0.74389,0.38726,0.89496,0.38557,0.63052,0.61327,0.69867,0.64517,0.80729,0.66671,0.89935,0.66517,0.95458,0.65748,0.28814,0.65521,0.40225,0.61593,0.50719,0.62362,0.62034,0.67541,0.24107,0.56424,0.25128,0.61439,0.47618,0.42651,0.40777,0.40046,0.38384,0.46972,0.82755,0.53435,0.41514,0.73136,0.64004,0.28944,0.70971,0.24655,0.74285,0.21885,0.75399,0.17094,0.79456,0.22595,0.81311,0.37496,0.6917,0.41989,0.49475,0.39051,0.94037,0.44945,0.49313,0.33602,0.47533,0.26494,0.52725,0.2877,0.52379,0.34898],"triangles":[3,1,2,3,38,1,3,37,38,4,36,3,3,36,37,36,4,42,5,6,26,6,30,26,5,26,49,49,26,25,25,39,49,4,5,42,42,35,36,5,49,42,42,49,41,6,29,30,28,29,6,26,30,25,30,29,25,25,28,44,28,25,29,28,27,44,28,6,7,39,40,49,49,40,41,25,44,39,42,34,35,42,41,34,37,36,48,36,35,48,38,37,0,1,38,0,39,24,40,39,44,24,28,7,27,34,23,35,35,23,48,48,23,31,22,31,56,22,56,32,48,31,22,23,34,41,41,40,19,40,24,19,27,43,44,44,43,24,23,41,19,0,37,48,19,18,47,19,24,18,24,43,18,43,27,17,18,43,17,19,45,23,23,45,31,31,45,57,48,58,0,48,22,58,19,47,45,18,17,47,16,17,7,27,7,17,11,0,14,47,46,45,47,17,46,31,57,56,32,55,22,22,33,58,22,55,33,33,14,58,0,58,14,45,46,57,46,17,16,56,57,32,46,16,57,8,16,7,57,16,59,16,15,59,32,12,20,32,57,12,57,62,12,57,59,62,55,32,21,33,55,14,32,20,21,14,55,54,62,61,12,12,50,20,12,61,50,55,21,54,14,54,11,62,59,61,59,15,61,20,51,21,20,50,51,16,60,15,16,8,60,15,60,61,51,50,10,9,10,50,51,52,21,13,21,52,13,54,21,61,9,50,61,60,9,60,8,9,52,51,53,54,13,11,52,53,13,53,51,10,13,53,11,53,10,11],"vertices":[2,11,43.55,-33.78,0.872,29,191.17,-59.05,0.128,2,11,33.35,-33.55,0.92,29,191.17,-69.26,0.08,1,11,-16.17,-32.46,1,2,11,-15.91,-20.93,0.936,29,179.64,-118.79,0.064,2,11,-15.54,-3.96,0.85658,29,162.67,-118.79,0.14342,2,11,-15.15,13.85,0.888,29,144.86,-118.79,0.112,1,11,-13.8,74.52,1,1,11,114.17,71.69,1,1,11,113.34,34.44,1,2,11,112.93,16.05,0.88,29,139.82,9.21,0.12,1,11,112.64,2.5,1,1,11,111.8,-35.28,1,3,11,67.27,14.77,0.79565,12,-1.29,12.52,0.10035,29,142.11,-36.42,0.104,2,11,86.03,-10.71,0.752,12,8.58,-17.54,0.248,3,11,66.62,-25.02,0.8983,12,-14.32,-25.09,0.072,29,181.91,-36.18,0.0297,2,11,72.73,21.57,0.776,12,6.03,17.27,0.224,1,11,71.94,27.6,1,1,11,59.45,35.25,1,1,11,47.97,37.77,1,2,11,46.98,27.21,0.808,29,130.12,-56.97,0.192,3,11,69.68,2.13,0.67046,12,-2.94,-0.24,0.19354,29,154.69,-33.73,0.136,3,11,77.57,-8.44,0.73498,12,1.26,-12.75,0.19302,29,165.09,-25.6,0.072,2,11,54.57,-14.17,0.656,29,171.33,-48.47,0.344,2,11,40.82,4.92,0.84,29,152.55,-62.64,0.16,2,11,36.91,38.8,0.808,29,118.76,-67.3,0.192,2,11,26.55,44.39,0.808,29,113.4,-77.78,0.192,2,11,13.75,45.6,0.752,29,112.47,-90.6,0.248,1,11,39.27,50.63,1,1,11,31.03,57.57,1,1,11,19.65,59.22,1,1,11,14.89,54.67,1,2,11,53.32,0.91,0.8,29,156.27,-50.06,0.2,3,11,62.85,-6.79,0.76736,12,-12.22,-6.59,0.11264,29,163.77,-40.36,0.12,2,11,62.71,-22.96,0.888,29,179.93,-40.14,0.112,2,11,34.19,5.97,0.76421,29,151.63,-69.29,0.23579,2,11,29.95,-1.22,0.73432,29,158.93,-73.37,0.26568,2,11,26.94,-12.78,0.70439,29,170.55,-76.13,0.29561,2,11,26.92,-22.64,0.75327,29,180.4,-75.93,0.24673,2,11,27.77,-28.57,0.8175,29,186.31,-74.95,0.1825,2,11,29.64,42.72,0.82064,29,115,-74.66,0.17936,2,11,34.39,30.4,0.82263,29,127.21,-69.63,0.17737,2,11,33.16,19.2,0.7856,29,138.44,-70.61,0.2144,2,11,26.27,7.24,0.78368,29,150.55,-77.24,0.21632,1,11,41.39,47.5,1,2,11,34.95,46.55,0.87739,29,111.06,-69.43,0.12261,3,11,58.46,21.96,0.81998,12,-7.41,22.1,0.05867,29,135.12,-45.38,0.12135,3,11,61.95,29.2,0.89275,12,-1.83,27.89,0.03852,29,127.8,-42.05,0.06873,2,11,53.15,31.96,0.88789,29,125.24,-50.91,0.11211,2,11,43.83,-15.32,0.65132,29,172.72,-59.19,0.34868,2,11,19.59,29.35,0.75785,29,128.59,-84.4,0.24215,3,11,75.61,4.04,0.70992,12,3.29,-0.28,0.17008,29,152.65,-27.84,0.12,3,11,80.94,-3.53,0.72268,12,5.98,-9.14,0.20532,29,160.11,-22.35,0.072,3,11,84.4,-7.16,0.72704,12,8.15,-13.66,0.21696,29,163.65,-18.8,0.056,2,11,90.51,-8.49,0.79373,12,13.53,-16.83,0.20628,3,11,83.37,-12.67,0.76954,12,5.45,-18.58,0.21403,29,169.19,-19.71,0.01644,3,11,64.26,-14.23,0.83522,12,-13.2,-14.09,0.04928,29,171.17,-38.78,0.1155,3,11,58.8,-1.12,0.7478,12,-14.29,0.07,0.04238,29,158.18,-44.53,0.20982,3,11,63.02,19.87,0.78263,12,-3.73,18.69,0.11049,29,137.11,-40.77,0.10688,2,11,54.43,-27.63,0.88108,29,184.79,-48.32,0.11892,2,11,70,19.89,0.84462,12,2.91,16.53,0.15538,2,11,79.14,21.59,0.79649,12,12.12,15.29,0.20351,3,11,76.1,16.1,0.76325,12,7.52,11.03,0.19925,29,140.58,-27.62,0.0375,3,11,68.27,16.64,0.81357,12,0.25,13.99,0.12049,29,140.21,-35.46,0.06593],"hull":12,"edges":[12,14,14,16,20,22,0,22,28,0,0,2,2,4,4,6,2,6,30,32,32,34,34,36,24,40,40,42,42,26,10,12,38,48,50,52,54,56,56,58,58,60,68,46,68,70,70,72,72,74,74,76,48,78,78,50,78,80,80,82,10,84,84,68,82,84,36,86,86,54,86,88,88,78,90,38,92,94,94,36,44,96,96,72,6,8,8,10,72,8,16,18,18,20,18,100,100,40,100,102,102,104,20,106,106,26,104,106,26,108,108,28,42,108,64,110,110,66,62,112,112,64,24,114,114,90,114,64,114,32,0,116,116,66,42,110,118,30,16,120,120,30,120,122,122,100,24,124,124,118,122,124],"width":107,"height":128}},"eye":{"eye":{"type":"mesh","uvs":[1,1,0,1,0,0,1,0],"triangles":[1,2,3,1,3,0],"vertices":[-5.63,-11.04,-0.53,10.36,8.22,8.28,3.13,-13.12],"hull":4,"edges":[0,2,2,4,4,6,0,6],"width":22,"height":9}},"frame_new":{"frame_new":{"x":99.42,"y":-127.99,"width":170,"height":134}},"frame_new_add":{"frame_new":{"x":99.42,"y":-127.99,"width":170,"height":134}},"frame_up":{"frame_up":{"x":99.55,"y":-191.26,"width":172,"height":9}},"head":{"head":{"type":"mesh","uvs":[1,0.69662,1,1,0,1,0,0,0.41692,0,0.56515,0,1,0,0.25114,0.51736,0.3059,0.52231,0.39814,0.45004,0.51535,0.45895,0.12912,0.49459,0.21751,0.55794,0.21079,0.7094,0.26075,0.73513,0.28381,0.71435,0.30975,0.71336,0.31839,0.69059,0.28381,0.66386,0.24826,0.78067,0.27708,0.79255,0.29054,0.76681,0.39526,0.7678,0.42312,0.75196,0.32608,0.846,0.27996,0.85194,0.23288,0.79651,0.1051,0.50053,0.08877,0.31245,0.1099,0.55398,0.13489,0.58269,0.13969,0.69554,0.31743,0.95984,0.377,0.9638,0.57396,0.8361,0.65082,0.75394,0.64986,0.67277,0.59318,0.52231,0.52881,0.6896,0.31551,0.56487,0.32896,0.53418,0.38949,0.50944,0.45002,0.50548,0.36643,0.56982,0.42024,0.54309,0.17278,0.29429,0.26607,0.3405,0.42575,0.38117,0.56389,0.48099,0.79533,0.40705,0.69486,0.30168,0.49033,0.16675,0.28939,0.14272,0.25351,0.14087,0.18533,0.2185,0.3791,0.06138,0.4706,0.02996,0.52622,0.02811,0.98605,0.48491,0.94298,0.76261,0.82763,0.79132,0.73972,0.74902,0.67992,0.6577,0.70345,0.6577,0.77168,0.55467,0.76815,0.48316,0.73403,0.42619,0.65286,0.45407,0.63639,0.4771,0.63403,0.55589,0.58933,0.61528,0.69992,0.09528,0.79168,0.18619,0.85756,0.38255,0.84815,0.46255,0.77033,0.5273,0.85459,0.40778,0.95168,0.44922,0.25633,0.05425,0.13555,0.15183,0.08064,0.28617,0.79689,0.61654,0.86042,0.71472,0.81793,0.4877,0.92218,0.54926,0.7227,0.62863,0.77042,0.7129,0.86683,0.78156],"triangles":[2,33,1,2,32,33,33,34,1,1,34,60,61,60,34,34,35,61,60,87,1,87,59,1,59,0,1,2,31,32,31,29,30,31,2,29,2,27,29,27,80,28,27,2,80,80,2,3,32,24,33,33,23,34,33,24,23,31,26,32,31,13,26,26,25,32,32,25,24,25,26,20,26,19,20,25,20,24,24,22,23,20,21,24,24,21,22,23,38,34,34,38,35,26,13,19,20,19,21,61,86,60,60,86,87,86,82,87,87,82,59,19,14,21,19,13,14,21,16,22,23,22,17,14,15,21,21,15,16,59,82,0,61,35,63,35,62,63,38,36,35,35,36,62,22,16,17,17,43,23,23,43,38,38,43,44,61,63,86,14,13,15,84,0,82,17,16,15,15,13,18,17,15,18,63,85,86,82,86,81,86,85,81,18,13,12,82,81,84,84,58,0,12,13,30,13,31,30,17,18,43,38,37,70,44,37,38,38,70,36,37,42,48,37,44,42,36,70,62,18,39,43,18,12,39,39,7,8,7,39,12,85,63,62,69,85,62,69,62,70,85,69,64,69,75,64,85,64,81,75,69,68,65,68,67,65,67,66,75,68,65,75,83,81,83,84,81,70,37,69,48,42,10,12,30,11,39,40,43,43,41,44,43,40,41,39,8,40,30,29,11,12,11,7,69,37,68,81,64,75,29,27,11,83,74,84,84,77,58,84,74,77,44,41,42,40,8,41,75,65,83,41,8,9,37,48,68,8,46,9,7,11,46,41,9,42,46,8,7,42,9,10,27,28,11,0,58,6,11,45,46,11,28,45,74,83,49,58,77,6,83,65,49,65,66,49,68,48,67,50,67,48,74,76,77,74,49,76,9,47,10,47,50,48,67,50,66,47,48,10,9,46,47,76,73,77,77,73,6,66,50,49,76,49,73,49,50,73,50,72,73,73,72,6,47,51,50,51,47,52,45,54,46,46,54,52,47,46,52,52,54,53,28,80,45,50,51,71,71,51,57,50,71,72,71,57,5,45,80,54,80,79,54,80,3,79,54,79,53,72,71,6,52,55,51,55,56,51,51,56,57,53,79,78,52,53,55,53,78,55,78,79,3,71,5,6,55,4,56,55,78,4,78,3,4,57,56,5,5,56,4],"vertices":[1,13,-2.11,-41.51,1,1,13,-31.05,-33.45,1,1,13,-3.67,64.81,1,1,13,91.7,38.24,1,1,13,80.28,-2.72,1,1,13,76.23,-17.29,1,1,13,64.32,-60.02,1,2,29,111.02,15.73,0.072,13,35.48,27.31,0.928,2,29,116.6,15.24,0.064,13,33.51,22.06,0.936,2,29,126.01,22.39,0.072,13,37.88,11.08,0.928,2,29,137.97,21.51,0.048,13,33.82,-0.2,0.952,2,29,98.57,17.98,0.04,13,40.99,38.7,0.96,2,29,107.59,11.71,0.072,13,32.53,31.69,0.928,2,29,106.9,-3.28,0.096,13,18.27,36.38,0.904,2,29,112,-5.83,0.064,13,14.45,32.15,0.936,2,29,114.35,-3.77,0.096,13,15.8,29.34,0.904,2,29,117,-3.67,0.064,13,15.19,26.76,0.936,2,29,117.88,-1.42,0.048,13,17.12,25.31,0.952,2,29,114.35,1.23,0.072,13,20.62,27.99,0.928,2,29,110.72,-10.34,0.064,13,10.45,34.59,0.936,2,29,113.66,-11.51,0.072,13,8.53,32.07,0.928,2,29,115.04,-8.97,0.064,13,10.61,30.07,0.936,2,29,125.72,-9.06,0.064,13,7.65,19.8,0.936,2,29,128.56,-7.5,0.072,13,8.4,16.65,0.928,2,29,118.66,-16.81,0.056,13,2.09,28.68,0.944,2,29,113.96,-17.39,0.056,13,2.78,33.37,0.944,2,29,109.16,-11.91,0.104,13,9.36,36.52,0.896,1,13,41.08,41.21,1,1,13,59.47,37.82,1,1,13,35.86,42.16,1,2,29,99.16,9.26,0.032,13,32.43,40.47,0.968,1,13,21.54,43,1,2,29,117.78,-28.08,0.032,13,-8.53,32.55,0.968,2,29,123.86,-28.47,0.056,13,-10.54,26.81,0.944,1,13,-3.75,4.06,1,2,29,151.79,-7.69,0.032,13,1.98,-5.67,0.968,2,29,151.69,0.34,0.064,13,9.75,-7.74,0.936,2,29,145.91,15.24,0.12,13,25.65,-6.16,0.88,2,29,139.34,-1.32,0.088,13,11.46,4.61,0.912,2,29,117.58,11.03,0.104,13,29.19,22.25,0.896,2,29,118.96,14.06,0.096,13,31.75,20.11,0.904,2,29,125.13,16.51,0.088,13,32.45,13.51,0.912,2,29,131.3,16.91,0.048,13,31.17,7.45,0.952,2,29,122.78,10.54,0.08,13,27.32,17.38,0.92,2,29,128.27,13.18,0.072,13,28.4,11.38,0.928,2,29,103.03,37.81,0.02375,13,58.9,29.09,0.97625,2,29,112.54,33.24,0.12729,13,51.94,21.15,0.87271,2,29,128.83,29.21,0.07788,13,43.69,6.54,0.92212,2,29,142.92,19.33,0.10699,13,30.39,-4.39,0.89301,2,29,166.53,26.65,0.03741,13,31.11,-29.09,0.96259,2,29,156.28,37.08,0.05287,13,43.9,-22.02,0.94713,2,29,135.42,50.44,0.08796,13,62.37,-5.51,0.91204,2,29,114.92,52.82,0.06083,13,70.16,13.6,0.93917,2,29,111.26,53,0.07646,13,71.32,17.08,0.92354,2,29,104.31,45.32,0.05697,13,65.78,25.84,0.94303,2,29,124.07,60.87,0.03787,13,75.47,2.62,0.96213,2,29,133.4,63.98,0.03487,13,75.96,-7.2,0.96513,2,29,139.08,64.17,0.06669,13,74.61,-12.72,0.93331,1,13,18.46,-45.76,1,1,13,-6.85,-34.15,1,2,29,169.82,-11.39,0.056,13,-6.43,-22.05,0.944,2,29,160.85,-7.2,0.05467,13,0.02,-14.54,0.94533,2,29,154.75,1.84,0.05571,13,10.36,-11.09,0.94429,2,29,157.15,1.84,0.06937,13,9.72,-13.4,0.93063,2,29,164.11,12.04,0.03205,13,17.67,-22.84,0.96795,2,29,163.75,19.12,0.032,13,24.59,-24.4,0.968,2,29,160.27,24.76,0.016,13,30.96,-22.56,0.984,2,29,151.99,22,0.09591,13,30.52,-13.84,0.90409,2,29,150.31,19.72,0.09029,13,28.78,-11.61,0.90971,2,29,150.07,11.92,0.09398,13,21.33,-9.29,0.90602,2,29,145.51,6.04,0.06872,13,16.89,-3.32,0.93128,2,29,156.79,57.52,0.04495,13,63.45,-28,0.95505,2,29,166.15,48.52,0.0354,13,52.27,-34.6,0.9646,1,13,31.74,-35.86,1,2,29,171.91,21.16,0.008,13,24.37,-32.81,0.992,2,29,163.98,14.75,0.03207,13,20.32,-23.44,0.96793,2,29,172.57,26.58,0.032,13,29.41,-34.89,0.968,2,29,182.47,22.48,0.00187,13,22.8,-43.33,0.99813,1,13,79.51,14.5,1,2,29,99.23,51.92,0.00678,13,73.51,28.96,0.99322,1,13,62.2,37.92,1,2,29,166.68,5.91,0.04899,13,11.08,-23.68,0.95101,2,29,173.16,-3.81,0.05065,13,-0.02,-27.31,0.94935,2,29,168.83,18.67,0.05392,13,22.8,-29.17,0.94608,2,29,179.46,12.57,0.01902,13,14.07,-37.78,0.98098,2,29,159.12,4.71,0.07361,13,11.96,-16.07,0.92639,2,29,163.98,-3.63,0.03784,13,2.62,-18.52,0.96216,2,29,173.82,-10.43,0.0714,13,-6.57,-26.17,0.9286],"hull":7,"edges":[2,4,4,6,14,16,16,18,18,20,22,24,24,26,26,28,28,30,30,32,32,34,34,36,38,40,40,42,42,44,44,46,46,48,48,50,50,52,52,38,22,54,56,54,54,58,58,60,60,62,62,64,64,66,66,68,68,70,70,72,74,76,78,80,80,82,82,84,78,86,86,88,88,84,90,92,92,94,94,96,98,100,100,102,102,104,104,106,90,108,108,106,106,110,110,112,112,114,2,0,0,12,116,0,0,118,120,122,124,126,130,132,132,134,134,136,136,138,138,140,142,144,144,146,128,150,150,130,146,152,152,148,152,154,154,116,10,12,142,10,6,8,8,10,8,156,156,158,158,160,150,162,162,164,164,118,148,166,166,150,166,168,168,0,126,170,170,128,170,172,118,174,174,120,172,174],"width":102,"height":99}},"hoop back":{"hoop 2":{"rotation":-116.99,"width":20,"height":25}},"hoop front":{"hoop front":{"x":0.75,"y":-1.2,"rotation":-116.99,"width":28,"height":28}},"knife hand":{"lewa reka":{"type":"mesh","uvs":[1,1,0.63037,1,0,1,0,0,1,0,0.57005,0.94036,0.40794,0.93549,0.72614,0.76422,0.53769,0.63587,0.48037,0.94691,0.39657,0.96853,0.22408,0.97154,0.22033,0.91433],"triangles":[8,3,4,7,8,4,12,3,8,6,12,8,8,9,6,7,5,8,5,9,8,10,12,6,11,12,10,2,3,12,2,12,11,1,5,7,9,5,1,10,6,9,1,10,9,11,10,1,2,11,1,7,4,0,1,7,0],"vertices":[42.71,-5.9,55.83,10.11,78.21,37.41,150.14,-21.54,114.64,-64.85,62.26,9.2,68.37,15.94,69.39,-7.94,85.31,-7.34,64.97,13.47,66.39,18.38,72.3,26.03,76.55,22.82],"hull":5,"edges":[4,6,6,8,0,8,0,2,2,4,2,10,0,14,14,16,10,18,18,12,12,20,20,22,22,24],"width":56,"height":93}},"mask":{"mask":{"type":"clipping","end":"knife hand","vertexCount":6,"vertices":[-37.36,28.16,226.26,19.44,226.21,-192.73,43.15,-192.24,38.09,-226.46,-43.52,-225.95],"color":"ce3a3aff"}},"right hand":{"prawa reka":{"type":"mesh","uvs":[1,1,0.59069,1,0,1,0,0.04252,0,0.02294,0,0,0.06079,0,1,0,0.10352,0.08755,0.1739,0.12475,0.18616,0.17774,0.16551,0.01968,0.29538,0.07907,0.33713,0.18558,0.07248,0.17592,0.50253,0.38421,0.02424,0.22102,0.05456,0.35092,0.17448,0.41642,0.21032,0.40568,0.08351,0.20169,0.07662,0.25,0.14278,0.29187,0.17724,0.23389,0.25718,0.28435,0.3771,0.31334,0.2048,0.21994,0.27372,0.45829,0.36056,0.48084,0.47839,0.35521,0.52934,0.41739,0.12987,0.197,0.25918,0.36122,0.39702,0.40846,0.42377,0.28962,0.39263,0.55319],"triangles":[11,6,7,4,5,6,3,4,6,8,6,11,3,6,8,14,3,8,8,11,9,14,8,9,12,11,7,9,11,12,10,9,12,14,9,10,10,12,13,31,14,10,26,10,13,23,10,26,27,28,35,13,12,7,20,14,31,16,3,14,16,14,20,23,31,10,21,16,20,24,26,13,23,26,24,34,13,7,25,24,13,22,31,23,22,23,24,21,20,31,22,21,31,34,25,13,17,16,21,17,21,22,32,24,25,22,24,32,19,22,32,18,17,22,29,33,25,29,25,34,32,25,33,19,18,22,27,32,33,19,32,27,28,27,33,16,17,2,2,17,18,18,19,27,2,18,27,29,34,7,15,29,7,30,15,7,35,28,33,33,29,15,33,15,30,35,33,30,3,16,2,0,1,30,35,30,1,2,27,35,2,35,1,0,30,7],"vertices":[1,24,-8.85,-11.7,1,1,24,6.05,14.67,1,1,24,27.55,52.73,1,1,28,9.73,2.38,1,1,28,10.27,0.6,1,2,26,23.86,14.26,0.00117,28,10.9,-1.48,0.99883,1,28,6.6,-2.79,1,3,24,73.87,-58.42,0.28647,25,12.58,-58.42,0.34979,27,-34.94,-46.34,0.36374,2,27,7.92,4.97,0.456,28,1.16,4.25,0.544,3,24,93.62,0.63,0.00002,26,9.76,3.91,0.11227,27,1.7,4.01,0.88771,3,24,88.79,2.32,0.00258,25,27.5,2.32,0.16,26,4.65,3.98,0.83742,3,25,41.32,-3.74,0.0003,27,8.96,-2.87,0.28988,28,-1.36,-3.25,0.70982,4,24,92.97,-9.33,0.01752,25,31.69,-9.33,0.01273,26,12.29,-5.75,0.3411,27,-1.92,-5.3,0.62865,3,24,82.65,-7.04,0.16315,25,21.36,-7.04,0.64857,26,1.77,-6.84,0.18828,3,24,93.08,9.55,0.0072,25,31.79,9.55,0.54398,26,6.43,12.21,0.44883,2,24,60.2,-8.42,0.65978,25,-1.09,-8.42,0.34022,3,24,91.1,14.77,0.00468,25,29.81,14.77,0.90175,26,2.91,16.53,0.09357,1,25,17.96,18.89,1,1,25,8.18,14.22,1,1,25,7.77,11.41,1,4,24,90.54,10.05,0.01124,25,29.25,10.05,0.51992,26,3.87,11.88,0.42084,28,-0.57,15.06,0.048,3,24,86.8,12.75,0.00296,25,25.51,12.75,0.95877,26,-0.53,13.26,0.03827,3,24,80.93,10.44,0.02428,25,19.64,10.44,0.83649,26,-5.38,9.22,0.13922,3,24,84.47,5.51,0.00396,25,23.18,5.51,0.84946,26,-0.46,5.66,0.14657,4,24,77.39,2.72,0.01696,25,16.1,2.72,0.88651,26,-6.3,0.77,0.08291,28,-15.15,18.84,0.01362,1,25,9.33,-3.65,1,3,24,84.62,3.09,0.00597,25,23.33,3.09,0.36451,26,0.45,3.4,0.62952,2,24,62.4,9.78,0.144,25,1.11,9.78,0.856,2,24,57.37,5.24,0.504,25,-3.92,5.24,0.496,3,24,63.47,-8.22,0.49461,25,2.18,-8.22,0.48625,26,-16.06,-14,0.01914,2,24,56.47,-8.6,0.81435,25,-4.81,-8.6,0.18565,4,24,89.24,6.84,0.00747,25,27.96,6.84,0.69035,26,3.65,8.42,0.279,28,-3.73,13.64,0.02318,4,24,70.95,6.18,0.0635,25,9.67,6.18,0.88529,26,-13.5,2.03,0.04399,28,-17.42,25.79,0.00723,3,24,62.03,-0.49,0.57624,25,0.74,-0.49,0.41612,26,-19.86,-7.12,0.00764,3,24,70.89,-7.77,0.08509,25,9.6,-7.77,0.89961,26,-9.17,-11.23,0.0153,2,24,50.22,6.56,0.72945,25,-11.07,6.56,0.27055],"hull":8,"edges":[0,14,8,10,4,6,6,8,6,16,16,18,18,20,10,12,12,14,12,22,22,24,24,26,20,28,28,32,32,34,34,36,36,38,40,42,42,44,44,38,46,48,48,50,20,52,38,54,54,56,0,2,2,4,58,30,0,60,60,30,40,62,62,46,26,68,68,58,2,70,70,56],"width":74,"height":95}},"wild_glow":{"wild_glow":{"type":"mesh","uvs":[1,1,0,1,0,0,1,0],"triangles":[1,2,3,1,3,0],"vertices":[1,15,58.35,-15.97,1,1,15,-54.65,-15.97,1,1,15,-54.65,16.03,1,1,15,58.35,16.03,1],"hull":4,"edges":[0,2,2,4,4,6,0,6],"width":113,"height":32}},"wlos 1":{"wlos 1":{"type":"mesh","uvs":[1,1,0.74003,1,0.62445,1,0,1,0,0.08895,0,0,0.19806,0,1,0,0.35217,0.12638,0.46519,0.30417,0.50372,0.5724,0.6039,0.82505,0.70407,0.86248,0.7837,0.82817,0.84792,0.67845,0.24055,0.28581,0.37272,0.49755,0.32713,0.75331,0.44978,0.77202,0.82737,0.91862,0.91666,0.77943,0.39908,0.91121,0.2784,0.55673,0.92081,0.50731],"triangles":[1,19,0,19,20,0,20,23,0,2,12,1,19,12,13,19,1,12,3,21,2,11,2,18,2,21,18,2,11,12,3,17,21,3,22,17,22,4,15,22,3,4,19,13,20,21,17,18,12,11,13,13,14,20,13,11,14,14,11,10,20,14,23,11,18,10,16,10,18,22,16,17,17,16,18,14,10,23,16,9,10,10,9,23,22,15,16,0,23,7,23,9,7,16,15,9,15,8,9,9,8,7,4,6,15,15,6,8,8,6,7,4,5,6],"vertices":[1,16,61.52,3.76,1,2,16,51.8,-5.26,0.896,29,140.73,4.58,0.104,2,16,47.48,-9.27,0.904,29,134.84,4.58,0.096,1,16,24.14,-30.93,1,2,16,-1.89,-2.89,0.936,29,102.99,42.85,0.064,2,16,-4.43,-0.15,0.96,29,102.99,46.58,0.04,2,16,2.97,6.72,0.96,29,113.09,46.58,0.04,1,16,32.95,34.54,1,2,16,12.35,8.18,0.872,29,120.95,41.28,0.128,2,16,21.65,6.63,0.888,29,126.72,33.81,0.112,2,16,30.75,-0.3,0.896,29,128.68,22.54,0.104,2,16,41.72,-4.6,0.936,29,133.79,11.93,0.064,2,16,46.53,-2.28,0.904,29,138.9,10.36,0.096,2,16,48.53,1.54,0.912,29,142.96,11.8,0.088,2,16,46.65,8.38,0.968,29,146.24,18.09,0.032,2,16,12.73,-0.6,0.928,29,115.26,34.58,0.072,2,16,23.72,-2.54,0.888,29,122,25.69,0.112,2,16,29.32,-11.99,0.832,29,119.68,14.94,0.168,2,16,34.44,-8.31,0.872,29,125.93,14.16,0.128,2,16,52.74,0.27,0.936,29,145.19,8,0.064,2,16,52.11,7.66,0.968,29,149.74,13.85,0.032,2,16,36.52,-14.36,0.7981,29,123.35,8.31,0.2019,2,16,21.88,-7.63,0.88276,29,117.19,23.2,0.11724,2,16,44.49,16.18,0.97787,29,149.95,25.28,0.02213],"hull":8,"edges":[0,14,10,12,12,14,12,16,16,18,18,20,20,22,22,24,24,26,26,28,6,8,8,10,8,30,30,32,32,36,4,6,36,4,0,2,2,4,2,38,38,40,40,28,34,42,30,44,44,34,40,46,46,28],"width":51,"height":42}},"wlos 2":{"wlos2":{"type":"mesh","uvs":[1,0.86269,1,1,0.76652,1,0,1,0,0,0.32911,0,1,0,0.1777,0.21339,0.21976,0.64625,0.50576,0.59988,0.48052,0.20566,0.20097,0.45288,0.49606,0.44837,0.46446,0.80458,0.80751,0.76033],"triangles":[10,5,6,7,4,5,7,5,10,12,10,6,11,7,10,11,10,12,14,9,12,9,8,11,9,11,12,6,14,12,13,8,9,13,9,14,14,6,0,11,3,4,11,4,7,3,11,8,3,8,13,2,13,14,2,14,0,3,13,2,2,0,1],"vertices":[1,17,32.36,7.89,1,1,17,37.37,7.01,1,1,17,36.68,3.11,1,1,17,34.44,-9.73,1,2,17,-2.01,-3.36,0.912,29,138.53,26.27,0.088,2,17,-1.04,2.16,0.904,29,144.13,26.27,0.096,1,17,0.92,13.39,1,2,17,6.29,-1.74,0.896,29,141.55,18.37,0.104,2,17,22.19,-3.8,0.96,29,142.27,2.36,0.04,2,17,21.34,1.29,0.976,29,147.13,4.07,0.024,2,17,6.9,3.38,0.952,29,146.7,18.66,0.048,2,17,15.09,-2.88,0.96,29,141.95,9.51,0.04,2,17,15.79,2.09,0.944,29,146.96,9.68,0.056,1,17,28.68,-0.71,1,1,17,28.07,5.32,1],"hull":7,"edges":[6,8,8,14,2,4,4,6,2,0,0,12,8,10,10,12,20,10,14,22,22,16,18,24,24,20,22,24,4,26,26,16,0,28,28,18,26,28],"width":17,"height":37}},"wlos 3":{"wlos 3":{"x":36.98,"y":5.57,"rotation":110.37,"width":25,"height":84}},"wlos 4":{"wlos 4":{"x":18.98,"y":7.72,"rotation":91.04,"width":24,"height":53}}}},"events":{"end_bounce_end":{},"high_win_end":{},"idle_end":{},"low_win_end":{},"medium_win_end":{},"no_win_end":{},"spin_end":{},"start_bounce_end":{}},"animations":{"sym1_2_win":{"slots":{"D2":{"color":[{"time":0.5667,"color":"ffffff00"},{"time":0.7,"color":"ffffffff"},{"time":0.8333,"color":"ffffff00"}]},"I2":{"color":[{"time":0.3667,"color":"ffffff00"},{"time":0.5,"color":"ffffffff"},{"time":0.6333,"color":"ffffff00"}]},"L2":{"color":[{"time":0.4667,"color":"ffffff00"},{"time":0.6,"color":"ffffffff"},{"time":0.7333,"color":"ffffff00"}]},"W2":{"color":[{"time":0.2667,"color":"ffffff00"},{"time":0.4,"color":"ffffffff"},{"time":0.5333,"color":"ffffff00"}]},"blink":{"color":[{"time":0,"color":"ffffff00","curve":"stepped"},{"time":0.3333,"color":"ffffff00"},{"time":0.5333,"color":"ffffffc5"},{"time":0.9,"color":"ffffff00","curve":"stepped"},{"time":1.5,"color":"ffffff00"}]},"blink2":{"color":[{"time":0.6667,"color":"ffffff00","curve":[0.263,-0.01,0.766,1.01]},{"time":0.8333,"color":"ffffff87","curve":[0.263,-0.01,0.766,1.01]},{"time":1.3333,"color":"ffffff00"}],"attachment":[{"time":0,"name":null},{"time":0.6667,"name":"blink"}]},"blink3":{"color":[{"time":0,"color":"ffffff00","curve":"stepped"},{"time":0.3667,"color":"ffffff00"},{"time":0.5667,"color":"ffffffc5"},{"time":0.8333,"color":"ffffff00","curve":"stepped"},{"time":1.5,"color":"ffffff00"}]},"blink4":{"color":[{"time":0,"color":"ffffff00","curve":"stepped"},{"time":0.5,"color":"ffffff00"},{"time":0.7,"color":"ffffffc5"},{"time":1.2667,"color":"ffffff00","curve":"stepped"},{"time":1.5,"color":"ffffff00"}]},"eye":{"color":[{"time":0.7333,"color":"ffffff00"},{"time":0.8333,"color":"ffffffff","curve":"stepped"},{"time":0.9333,"color":"ffffffff"}],"attachment":[{"time":0,"name":null},{"time":0.7333,"name":"eye"},{"time":0.9333,"name":null}]},"frame_new_add":{"color":[{"time":0.3333,"color":"ffffff00"},{"time":0.5,"color":"ffffffb4"},{"time":0.6667,"color":"ffffff00"}]}},"bones":{"WILD_text":{"rotate":[{"time":0,"angle":0,"curve":"stepped"},{"time":1.5,"angle":0}],"translate":[{"time":0,"x":0,"y":0,"curve":"stepped"},{"time":1.5,"x":0,"y":0}],"scale":[{"time":0,"x":1,"y":1,"curve":"stepped"},{"time":1.5,"x":1,"y":1}],"shear":[{"time":0,"x":0,"y":0,"curve":"stepped"},{"time":1.5,"x":0,"y":0}]},"glow":{"rotate":[{"time":0,"angle":0,"curve":"stepped"},{"time":1.5,"angle":0}],"translate":[{"time":0,"x":0,"y":0,"curve":"stepped"},{"time":1.5,"x":0,"y":0}],"scale":[{"time":0,"x":1,"y":1,"curve":"stepped"},{"time":0.2333,"x":1,"y":1},{"time":0.7667,"x":1,"y":1.5},{"time":1.2667,"x":1,"y":1,"curve":"stepped"},{"time":1.5,"x":1,"y":1}],"shear":[{"time":0,"x":0,"y":0,"curve":"stepped"},{"time":1.5,"x":0,"y":0}]},"W":{"rotate":[{"time":0,"angle":0,"curve":"stepped"},{"time":1.5,"angle":0}],"translate":[{"time":0,"x":0,"y":0,"curve":"stepped"},{"time":1.5,"x":0,"y":0}],"scale":[{"time":0,"x":1,"y":1,"curve":"stepped"},{"time":0.1667,"x":1,"y":1},{"time":0.4,"x":1.5,"y":1.5},{"time":0.6333,"x":1,"y":1,"curve":"stepped"},{"time":1.5,"x":1,"y":1}],"shear":[{"time":0,"x":0,"y":0,"curve":"stepped"},{"time":1.5,"x":0,"y":0}]},"L":{"rotate":[{"time":0,"angle":0,"curve":"stepped"},{"time":1.5,"angle":0}],"translate":[{"time":0,"x":0,"y":0,"curve":"stepped"},{"time":1.5,"x":0,"y":0}],"scale":[{"time":0,"x":1,"y":1,"curve":"stepped"},{"time":0.3667,"x":1,"y":1},{"time":0.6,"x":1.5,"y":1.5},{"time":0.8333,"x":1,"y":1,"curve":"stepped"},{"time":1.5,"x":1,"y":1}],"shear":[{"time":0,"x":0,"y":0,"curve":"stepped"},{"time":1.5,"x":0,"y":0}]},"I":{"rotate":[{"time":0,"angle":0,"curve":"stepped"},{"time":1.5,"angle":0}],"translate":[{"time":0,"x":0,"y":0,"curve":"stepped"},{"time":1.5,"x":0,"y":0}],"scale":[{"time":0,"x":1,"y":1,"curve":"stepped"},{"time":0.2667,"x":1,"y":1},{"time":0.5,"x":1.5,"y":1.5},{"time":0.7333,"x":1,"y":1,"curve":"stepped"},{"time":1.5,"x":1,"y":1}],"shear":[{"time":0,"x":0,"y":0,"curve":"stepped"},{"time":1.5,"x":0,"y":0}]},"D":{"rotate":[{"time":0,"angle":0,"curve":"stepped"},{"time":1.5,"angle":0}],"translate":[{"time":0,"x":0,"y":0,"curve":"stepped"},{"time":1.5,"x":0,"y":0}],"scale":[{"time":0,"x":1,"y":1,"curve":"stepped"},{"time":0.4667,"x":1,"y":1},{"time":0.7,"x":1.5,"y":1.5},{"time":0.9333,"x":1,"y":1,"curve":"stepped"},{"time":1.5,"x":1,"y":1}],"shear":[{"time":0,"x":0,"y":0,"curve":"stepped"},{"time":1.5,"x":0,"y":0}]},"blink":{"rotate":[{"time":0,"angle":0,"curve":"stepped"},{"time":0.2667,"angle":0},{"time":0.5333,"angle":41.94},{"time":0.8,"angle":119.82},{"time":1.5,"angle":0}],"translate":[{"time":0,"x":0,"y":0},{"time":0.3333,"x":-4.68,"y":8.97},{"time":0.5333,"x":-3.47,"y":4.64},{"time":0.9,"x":10.96,"y":-16.35},{"time":1.5,"x":0,"y":0}],"scale":[{"time":0.3333,"x":0.592,"y":0.592},{"time":0.5333,"x":2.268,"y":2.268},{"time":0.8333,"x":0.592,"y":0.592}]},"blink2":{"rotate":[{"time":0,"angle":0,"curve":"stepped"},{"time":0.3667,"angle":0},{"time":0.5667,"angle":41.94},{"time":0.8333,"angle":119.82},{"time":1.5,"angle":0}],"translate":[{"time":0,"x":0,"y":0},{"time":0.3667,"x":-4.29,"y":1.56},{"time":0.5667,"x":-1.06,"y":16.59},{"time":0.8333,"x":-5.43,"y":-4.78},{"time":1.5,"x":0,"y":0}],"scale":[{"time":0.3667,"x":0.592,"y":0.592},{"time":0.5667,"x":2.384,"y":2.384},{"time":0.8333,"x":0.592,"y":0.592}]},"blink3":{"rotate":[{"time":0,"angle":0,"curve":"stepped"},{"time":0.5,"angle":0},{"time":0.7,"angle":41.94},{"time":1.1333,"angle":119.82},{"time":1.5,"angle":0}],"translate":[{"time":0,"x":0,"y":0},{"time":0.5,"x":1.96,"y":2.13},{"time":0.7,"x":4.1,"y":9.71},{"time":1.1333,"x":4.88,"y":-11.87},{"time":1.5,"x":0,"y":0}],"scale":[{"time":0.5,"x":0.592,"y":0.592},{"time":0.7,"x":2.384,"y":2.384},{"time":1.2667,"x":0.592,"y":0.592}]},"body":{"rotate":[{"time":0,"angle":0,"curve":[0.27,-0.01,0.623,0.42]},{"time":0.3333,"angle":3.53,"curve":"stepped"},{"time":1.1667,"angle":3.53,"curve":[0.263,-0.01,0.766,1.01]},{"time":1.5,"angle":0}],"translate":[{"time":0,"x":0,"y":0}]},"neck":{"rotate":[{"time":0,"angle":0,"curve":"stepped"},{"time":0.1667,"angle":0,"curve":[0.291,-0.01,0.631,0.37]},{"time":0.5,"angle":8.47,"curve":[0.314,0.26,0.652,0.61]},{"time":0.8333,"angle":7.52,"curve":"stepped"},{"time":1.1667,"angle":7.52,"curve":[0.263,-0.01,0.766,1.01]},{"time":1.5,"angle":0}],"translate":[{"time":0,"x":0,"y":0}]},"head2":{"rotate":[{"time":0,"angle":0,"curve":"stepped"},{"time":0.3333,"angle":0,"curve":[0.263,-0.01,0.766,1.01]},{"time":0.6667,"angle":-12.65,"curve":"stepped"},{"time":1.1667,"angle":-12.65,"curve":[0.328,0.31,0.663,0.65]},{"time":1.5,"angle":0}],"translate":[{"time":0,"x":0,"y":0,"curve":[0.263,-0.01,0.766,1.01]},{"time":0.6667,"x":-1.65,"y":-2.38,"curve":"stepped"},{"time":1.1667,"x":-1.65,"y":-2.38,"curve":[0.263,-0.01,0.766,1.01]},{"time":1.5,"x":0,"y":0}]},"knife hand":{"rotate":[{"time":0,"angle":0},{"time":0.5,"angle":1.2},{"time":0.8333,"angle":4.15},{"time":1.5,"angle":0}]},"blink gun":{"rotate":[{"time":0,"angle":0,"curve":"stepped"},{"time":0.6667,"angle":0,"curve":[0.263,-0.01,0.766,1.01]},{"time":1.1667,"angle":180}],"translate":[{"time":0,"x":35.1,"y":-100.86,"curve":"stepped"},{"time":0.6667,"x":35.1,"y":-100.86,"curve":[0.257,-0.01,0.632,0.5]},{"time":0.8333,"x":31.51,"y":-123.77,"curve":[0.384,0.5,0.761,1.01]},{"time":1.3333,"x":35.49,"y":-148.01}],"scale":[{"time":0.6667,"x":1,"y":1,"curve":[0.263,-0.01,0.766,1.01]},{"time":0.8333,"x":2,"y":2,"curve":[0.263,-0.01,0.766,1.01]},{"time":1.1667,"x":1,"y":1}]},"eteRight":{"translate":[{"time":0,"x":-0.42,"y":-0.08,"curve":"stepped"},{"time":0.7333,"x":-0.42,"y":-0.08,"curve":[0.263,-0.01,0.766,1.01]},{"time":0.8333,"x":-0.77,"y":-1.53}]},"right hand":{"rotate":[{"time":0,"angle":0,"curve":[0.223,0.01,0.736,0.98]},{"time":0.6667,"angle":-11.43,"curve":"stepped"},{"time":0.8333,"angle":-11.43,"curve":[0.223,0.01,0.736,0.98]},{"time":1.5,"angle":0}],"translate":[{"time":0,"x":0,"y":0,"curve":[0.223,0.01,0.736,0.98]},{"time":0.6667,"x":-14.72,"y":-5.22,"curve":[0.271,0.02,0.614,0.4]},{"time":1,"x":-13.54,"y":-9.14,"curve":[0.304,0.28,0.747,0.99]},{"time":1.5,"x":0,"y":0}]},"right hand2":{"rotate":[{"time":0,"angle":0},{"time":0.6667,"angle":52.76},{"time":1.3333,"angle":72.06},{"time":1.5,"angle":0}]},"right hand finger1":{"rotate":[{"time":0,"angle":0,"curve":[0.263,-0.01,0.766,1.01]},{"time":0.6667,"angle":0.59,"curve":[0.263,-0.01,0.766,1.01]},{"time":1.3333,"angle":40.32,"curve":[0.263,-0.01,0.766,1.01]},{"time":1.5,"angle":0}]},"right hand finger2":{"rotate":[{"time":0,"angle":0,"curve":[0.263,-0.01,0.766,1.01]},{"time":0.6667,"angle":-24.94,"curve":"stepped"},{"time":0.7333,"angle":-24.94,"curve":[0.263,-0.01,0.766,1.01]},{"time":1.3333,"angle":40.32,"curve":[0.263,-0.01,0.766,1.01]},{"time":1.5,"angle":0}]},"right hand finger3":{"rotate":[{"time":0,"angle":0,"curve":[0.263,-0.01,0.766,1.01]},{"time":0.6667,"angle":-24.94,"curve":[0.263,-0.01,0.766,1.01]},{"time":1.3333,"angle":40.32,"curve":[0.263,-0.01,0.766,1.01]},{"time":1.5,"angle":0}]},"target":{"translate":[{"time":0,"x":0,"y":0,"curve":[0.263,-0.01,0.766,1.01]},{"time":0.5,"x":20.21,"y":0,"curve":"stepped"},{"time":1,"x":20.21,"y":0,"curve":[0.263,-0.01,0.766,1.01]},{"time":1.5,"x":0,"y":0}]},"hoop front":{"rotate":[{"time":0,"angle":0,"curve":[0.263,-0.01,0.766,1.01]},{"time":0.4333,"angle":16.77,"curve":[0.254,0,0.644,0.55]},{"time":0.8333,"angle":0.65,"curve":[0.389,0.54,0.753,1.01]},{"time":1.1667,"angle":1.85,"curve":[0.389,0.54,0.753,1.01]},{"time":1.5,"angle":0}],"translate":[{"time":0,"x":0,"y":0,"curve":[0.263,-0.01,0.766,1.01]},{"time":0.4333,"x":-2.89,"y":-5.68,"curve":[0.254,0,0.644,0.55]},{"time":0.8333,"x":-1.15,"y":-2.25,"curve":"stepped"},{"time":1.1667,"x":-1.15,"y":-2.25,"curve":[0.389,0.54,0.753,1.01]},{"time":1.5,"x":0,"y":0}],"scale":[{"time":0,"x":1,"y":1,"curve":[0.263,-0.01,0.766,1.01]},{"time":0.4333,"x":1,"y":0.894,"curve":[0.254,0,0.644,0.55]},{"time":0.8333,"x":1,"y":0.905,"curve":[0.389,0.54,0.753,1.01]},{"time":1.1667,"x":1,"y":0.958,"curve":[0.389,0.54,0.753,1.01]},{"time":1.5,"x":1,"y":1}]},"hair2":{"rotate":[{"time":0,"angle":0,"curve":[0.263,-0.01,0.766,1.01]},{"time":0.3333,"angle":-350.4,"curve":[0.263,-0.01,0.766,1.01]},{"time":0.6667,"angle":-4.8,"curve":[0.263,-0.01,0.766,1.01]},{"time":1,"angle":0,"curve":"stepped"},{"time":1.5,"angle":0}]},"hair3":{"rotate":[{"time":0,"angle":0,"curve":[0.263,-0.01,0.766,1.01]},{"time":0.3333,"angle":4.8,"curve":[0.263,-0.01,0.766,1.01]},{"time":0.6667,"angle":-2.4,"curve":[0.263,-0.01,0.766,1.01]},{"time":1,"angle":0}]},"hair4":{"rotate":[{"time":0,"angle":0,"curve":[0.263,-0.01,0.766,1.01]},{"time":0.3333,"angle":4.8,"curve":[0.263,-0.01,0.766,1.01]},{"time":0.6667,"angle":-2.4,"curve":[0.263,-0.01,0.766,1.01]},{"time":1,"angle":0}]},"hoop back":{"rotate":[{"time":0,"angle":0,"curve":[0.263,-0.01,0.766,1.01]},{"time":0.5,"angle":11.97,"curve":[0.254,0,0.644,0.55]},{"time":0.8333,"angle":0.65,"curve":[0.389,0.54,0.753,1.01]},{"time":1.1667,"angle":1.85,"curve":[0.389,0.54,0.753,1.01]},{"time":1.5,"angle":0}],"translate":[{"time":0,"x":0,"y":0,"curve":[0.263,-0.01,0.766,1.01]},{"time":0.5,"x":-2.89,"y":-5.68,"curve":[0.254,0,0.644,0.55]},{"time":0.8333,"x":-1.15,"y":-2.25,"curve":"stepped"},{"time":1.1667,"x":-1.15,"y":-2.25,"curve":[0.389,0.54,0.753,1.01]},{"time":1.5,"x":0,"y":0}]},"D2":{"rotate":[{"time":0,"angle":0,"curve":"stepped"},{"time":1.5,"angle":0}],"translate":[{"time":0,"x":0,"y":0,"curve":"stepped"},{"time":1.5,"x":0,"y":0}],"scale":[{"time":0,"x":1,"y":1,"curve":"stepped"},{"time":0.4667,"x":1,"y":1},{"time":0.7,"x":1.5,"y":1.5},{"time":0.9333,"x":1,"y":1,"curve":"stepped"},{"time":1.5,"x":1,"y":1}],"shear":[{"time":0,"x":0,"y":0,"curve":"stepped"},{"time":1.5,"x":0,"y":0}]},"I2":{"rotate":[{"time":0,"angle":0,"curve":"stepped"},{"time":1.5,"angle":0}],"translate":[{"time":0,"x":0,"y":0,"curve":"stepped"},{"time":1.5,"x":0,"y":0}],"scale":[{"time":0,"x":1,"y":1,"curve":"stepped"},{"time":0.2667,"x":1,"y":1},{"time":0.5,"x":1.5,"y":1.5},{"time":0.7333,"x":1,"y":1,"curve":"stepped"},{"time":1.5,"x":1,"y":1}],"shear":[{"time":0,"x":0,"y":0,"curve":"stepped"},{"time":1.5,"x":0,"y":0}]},"L2":{"rotate":[{"time":0,"angle":0,"curve":"stepped"},{"time":1.5,"angle":0}],"translate":[{"time":0,"x":0,"y":0,"curve":"stepped"},{"time":1.5,"x":0,"y":0}],"scale":[{"time":0,"x":1,"y":1,"curve":"stepped"},{"time":0.3667,"x":1,"y":1},{"time":0.6,"x":1.5,"y":1.5},{"time":0.8333,"x":1,"y":1,"curve":"stepped"},{"time":1.5,"x":1,"y":1}],"shear":[{"time":0,"x":0,"y":0,"curve":"stepped"},{"time":1.5,"x":0,"y":0}]},"W2":{"rotate":[{"time":0,"angle":0,"curve":"stepped"},{"time":1.5,"angle":0}],"translate":[{"time":0,"x":0,"y":0,"curve":"stepped"},{"time":1.5,"x":0,"y":0}],"scale":[{"time":0,"x":1,"y":1,"curve":"stepped"},{"time":0.1667,"x":1,"y":1},{"time":0.4,"x":1.5,"y":1.5},{"time":0.6333,"x":1,"y":1,"curve":"stepped"},{"time":1.5,"x":1,"y":1}],"shear":[{"time":0,"x":0,"y":0,"curve":"stepped"},{"time":1.5,"x":0,"y":0}]}},"deform":{"default":{"eye":{"eye":[{"time":0,"vertices":[11.07939,18.87439,2.78815,-19.72992,-14.79634,-15.90063,-6.50535,22.70365],"curve":"stepped"},{"time":0.7333,"vertices":[11.07939,18.87439,2.78815,-19.72992,-14.79634,-15.90063,-6.50535,22.70365]}]},"head":{"head":[{"time":0,"curve":"stepped"},{"time":0.6667,"curve":[0.263,-0.01,0.766,1.01]},{"time":0.8,"offset":14,"vertices":[0.30757,-0.48152,-0.5464,-0.16705,1.28169,-0.25827,-0.59276,-1.16535,0.56042,0.99612,0.80917,-0.80718,0,0,0,0,0,0,0,0,0,0,0,0,0,0,0,0,0,0,0,0,0,0,0,0,0,0,0,0,0,0,0,0,0,0,0,0,0,0,0,0,0,0,0,0,0,0,0,0,-0.22327,0.97417,0.99835,-0.04635,1.05573,0.81387,0.50069,-1.23541,1.07486,0.12807,-0.1651,-1.0698,0,0,0,0,0,0,0,0,0,0,0,0,0,0,0,0,0,0,0,0,0,0,0,0,0,0,0,0,0,0,0,0,0,0,0,0,0,0,0,0,0,0,0,0,0,0,0,0,0,0,2.71881,-2.57103,-3.20636,-1.92908,2.03035,-2.49217,-2.94563,-1.28705,0,0,0,0,-0.70757,0.7646,0.92644,0.47642,-0.8165,1.15366,1.33044,0.47694],"curve":"stepped"},{"time":0.8667,"offset":14,"vertices":[0.30757,-0.48152,-0.5464,-0.16705,1.28169,-0.25827,-0.59276,-1.16535,0.56042,0.99612,0.80917,-0.80718,0,0,0,0,0,0,0,0,0,0,0,0,0,0,0,0,0,0,0,0,0,0,0,0,0,0,0,0,0,0,0,0,0,0,0,0,0,0,0,0,0,0,0,0,0,0,0,0,-0.22327,0.97417,0.99835,-0.04635,1.05573,0.81387,0.50069,-1.23541,1.07486,0.12807,-0.1651,-1.0698,0,0,0,0,0,0,0,0,0,0,0,0,0,0,0,0,0,0,0,0,0,0,0,0,0,0,0,0,0,0,0,0,0,0,0,0,0,0,0,0,0,0,0,0,0,0,0,0,0,0,2.71881,-2.57103,-3.20636,-1.92908,2.03035,-2.49217,-2.94563,-1.28705,0,0,0,0,-0.70757,0.7646,0.92644,0.47642,-0.8165,1.15366,1.33044,0.47694],"curve":[0.263,-0.01,0.766,1.01]},{"time":1}]},"knife hand":{"lewa reka":[{"time":0}]},"right hand":{"prawa reka":[{"time":0,"curve":[0.223,0.01,0.736,0.98]},{"time":0.6667,"offset":2,"vertices":[-1.14693,1.86187,0,0,0,0,0,0,0,0,0,0,0,0,0,0,0,0,0,0,0,0,0,0,0,0,0,0,0,0,0,0,0,0,0,0,0,0,0,0,0,0,0,0,0,0,0,0,0,0,0,0,0,0,0,0,0,0,0,0,0,0,0,0,0,0,0,0,0,0,0,0,0,0,0,0,0,0,0,0,0,0,0,0,0,0,0,0,0,0,0,0,0,0,0,0,0,0,0,0,0,0,0,0,0,0,0,0,0,0,0,0,0,0,0,0,0,0,0,0,-0.72345,1.82708,1.31308,1.46202,-3.11586,3.90875,2.11005,4.53166,0,0,0,0,0,0,0,0,0,0,0,0,0,0,0,0,0,0,0,0,0,0,0,0,0,0,0,0,0,0,0,0,0.99982,-0.14052,0.31973,-0.95761,0.43437,-0.91148,-3.11301,4.33411,2.49222,4.71847],"curve":[0.223,0.01,0.736,0.98]},{"time":1.3333,"offset":2,"vertices":[-0.77167,2.26991,0,0,0,0,0,0,0,0,0,0,0,0,0,0,0,0,0,0,0,0,0,0,0,0,0,0,0,0,0,0,0,0,0,0,0,0,0,0,0,0,0,0,0,0,0,0,0,0,0,0,0,0,0,0,0,0,0,0,0,0,0,0,0,0,0,0,0,0,0,0,0,0,0,0,1.73442,-0.82953,0,0,0,0,0,0,0,0,0,0,0,0,0,0,0,0,0,0,0,0,0,0,0,0,0,0,0,0,0,0,0,0,0,0,0,0,0,0,0,0,0,0,-2.42633,4.55877,4.11642,3.04579,-5.33223,5.22992,3.66624,6.08037,0,0,0,0,0,0,0,0,0,0,0,0,0,0,0,0,0,0,0,0,0,0,0,0,0,0,-3.07495,0.33517,0.46868,3.0584,1.57696,2.66089,0.99982,-0.14052,0.31973,-0.95761,0.43437,-0.91148,-2.73775,4.74216,3.63827,3.53448],"curve":[0.224,0,0.738,0.99]},{"time":1.5}]}}}}}}